[
  {
    "line": 1,
    "elements": [
      {
        "start_timestamp": "2021-05-04T04:54:42.813Z",
        "before": [
          {
            "result": {
              "duration": 6335000000,
              "status": "passed"
            },
            "match": {
              "location": "com.tau.steps.GooglePageStep.setup() in file:/C:/Users/achat/IdeaProjects/tau-cucumber-course/target/test-classes/"
            }
          }
        ],
        "line": 3,
        "name": "google page search",
        "description": "",
        "id": "this-is-simple-google-page-search;google-page-search",
        "after": [
          {
            "result": {
              "duration": 600000000,
              "status": "passed"
            },
            "match": {
              "location": "com.tau.steps.GooglePageStep.closeDriver() in file:/C:/Users/achat/IdeaProjects/tau-cucumber-course/target/test-classes/"
            }
          }
        ],
        "type": "scenario",
        "keyword": "Scenario",
        "steps": [
          {
            "result": {
              "duration": 2198000000,
              "status": "passed"
            },
            "line": 4,
            "name": "open url \"https://facebook.com\"",
            "match": {
              "arguments": [
                {
                  "val": "\"https://facebook.com\"",
                  "offset": 9
                }
              ],
              "location": "com.tau.steps.GooglePageStep.openUrl(String) in file:/C:/Users/achat/IdeaProjects/tau-cucumber-course/target/test-classes/"
            },
            "keyword": "Given "
          },
          {
            "result": {
              "duration": 7190000000,
              "status": "passed"
            },
            "line": 5,
            "name": "open url \"https://youtube.com\"",
            "match": {
              "arguments": [
                {
                  "val": "\"https://youtube.com\"",
                  "offset": 9
                }
              ],
              "location": "com.tau.steps.GooglePageStep.openUrl(String) in file:/C:/Users/achat/IdeaProjects/tau-cucumber-course/target/test-classes/"
            },
            "keyword": "And "
          },
          {
            "result": {
              "duration": 4331000000,
              "status": "passed"
            },
            "line": 6,
            "name": "open url \"https://gmail.com\"",
            "match": {
              "arguments": [
                {
                  "val": "\"https://gmail.com\"",
                  "offset": 9
                }
              ],
              "location": "com.tau.steps.GooglePageStep.openUrl(String) in file:/C:/Users/achat/IdeaProjects/tau-cucumber-course/target/test-classes/"
            },
            "keyword": "And "
          },
          {
            "result": {
              "duration": 4527000000,
              "status": "passed"
            },
            "line": 7,
            "name": "open url \"https://programesecure.com\"",
            "match": {
              "arguments": [
                {
                  "val": "\"https://programesecure.com\"",
                  "offset": 9
                }
              ],
              "location": "com.tau.steps.GooglePageStep.openUrl(String) in file:/C:/Users/achat/IdeaProjects/tau-cucumber-course/target/test-classes/"
            },
            "keyword": "And "
          }
        ]
      }
    ],
    "name": "This is simple google page search",
    "description": "",
    "id": "this-is-simple-google-page-search",
    "keyword": "Feature",
    "uri": "file:src/test/resources/google.feature",
    "tags": []
  },
  {
    "line": 1,
    "elements": [
      {
        "start_timestamp": "2021-05-04T04:54:42.813Z",
        "before": [
          {
            "result": {
              "duration": 6325000000,
              "status": "passed"
            },
            "match": {
              "location": "com.tau.steps.GooglePageStep.setup() in file:/C:/Users/achat/IdeaProjects/tau-cucumber-course/target/test-classes/"
            }
          }
        ],
        "line": 3,
        "name": "google page search",
        "description": "",
        "id": "this-is-simple-google-page-search;google-page-search",
        "after": [
          {
            "result": {
              "duration": 370000000,
              "status": "passed"
            },
            "match": {
              "location": "com.tau.steps.GooglePageStep.closeDriver() in file:/C:/Users/achat/IdeaProjects/tau-cucumber-course/target/test-classes/"
            }
          }
        ],
        "type": "scenario",
        "keyword": "Scenario",
        "steps": [
          {
            "result": {
              "duration": 2288000000,
              "status": "passed"
            },
            "line": 4,
            "name": "open url \"https://facebook.com\"",
            "match": {
              "arguments": [
                {
                  "val": "\"https://facebook.com\"",
                  "offset": 9
                }
              ],
              "location": "com.tau.steps.GooglePageStep.openUrl(String) in file:/C:/Users/achat/IdeaProjects/tau-cucumber-course/target/test-classes/"
            },
            "keyword": "Given "
          },
          {
            "result": {
              "duration": 7655000000,
              "status": "passed"
            },
            "line": 5,
            "name": "open url \"https://youtube.com\"",
            "match": {
              "arguments": [
                {
                  "val": "\"https://youtube.com\"",
                  "offset": 9
                }
              ],
              "location": "com.tau.steps.GooglePageStep.openUrl(String) in file:/C:/Users/achat/IdeaProjects/tau-cucumber-course/target/test-classes/"
            },
            "keyword": "And "
          },
          {
            "result": {
              "duration": 4817000000,
              "status": "passed"
            },
            "line": 6,
            "name": "open url \"https://gmail.com\"",
            "match": {
              "arguments": [
                {
                  "val": "\"https://gmail.com\"",
                  "offset": 9
                }
              ],
              "location": "com.tau.steps.GooglePageStep.openUrl(String) in file:/C:/Users/achat/IdeaProjects/tau-cucumber-course/target/test-classes/"
            },
            "keyword": "And "
          },
          {
            "result": {
              "duration": 3851000000,
              "status": "passed"
            },
            "line": 7,
            "name": "open url \"https://programesecure.com\"",
            "match": {
              "arguments": [
                {
                  "val": "\"https://programesecure.com\"",
                  "offset": 9
                }
              ],
              "location": "com.tau.steps.GooglePageStep.openUrl(String) in file:/C:/Users/achat/IdeaProjects/tau-cucumber-course/target/test-classes/"
            },
            "keyword": "And "
          }
        ]
      }
    ],
    "name": "This is simple google page search",
    "description": "",
    "id": "this-is-simple-google-page-search",
    "keyword": "Feature",
    "uri": "file:src/test/resources/google1.feature",
    "tags": []
  },
  {
    "line": 1,
    "elements": [
      {
        "start_timestamp": "2021-05-04T04:54:42.813Z",
        "before": [
          {
            "result": {
              "duration": 6323000000,
              "status": "passed"
            },
            "match": {
              "location": "com.tau.steps.GooglePageStep.setup() in file:/C:/Users/achat/IdeaProjects/tau-cucumber-course/target/test-classes/"
            }
          }
        ],
        "line": 3,
        "name": "google page search",
        "description": "",
        "id": "this-is-simple-google-page-search;google-page-search",
        "after": [
          {
            "result": {
              "duration": 163000000,
              "status": "passed"
            },
            "match": {
              "location": "com.tau.steps.GooglePageStep.closeDriver() in file:/C:/Users/achat/IdeaProjects/tau-cucumber-course/target/test-classes/"
            }
          }
        ],
        "type": "scenario",
        "keyword": "Scenario",
        "steps": [
          {
            "result": {
              "duration": 2274000000,
              "status": "passed"
            },
            "line": 4,
            "name": "open url \"https://facebook.com\"",
            "match": {
              "arguments": [
                {
                  "val": "\"https://facebook.com\"",
                  "offset": 9
                }
              ],
              "location": "com.tau.steps.GooglePageStep.openUrl(String) in file:/C:/Users/achat/IdeaProjects/tau-cucumber-course/target/test-classes/"
            },
            "keyword": "Given "
          },
          {
            "result": {
              "duration": 8747000000,
              "status": "passed"
            },
            "line": 5,
            "name": "open url \"https://youtube.com\"",
            "match": {
              "arguments": [
                {
                  "val": "\"https://youtube.com\"",
                  "offset": 9
                }
              ],
              "location": "com.tau.steps.GooglePageStep.openUrl(String) in file:/C:/Users/achat/IdeaProjects/tau-cucumber-course/target/test-classes/"
            },
            "keyword": "And "
          },
          {
            "result": {
              "duration": 4213000000,
              "status": "passed"
            },
            "line": 6,
            "name": "open url \"https://gmail.com\"",
            "match": {
              "arguments": [
                {
                  "val": "\"https://gmail.com\"",
                  "offset": 9
                }
              ],
              "location": "com.tau.steps.GooglePageStep.openUrl(String) in file:/C:/Users/achat/IdeaProjects/tau-cucumber-course/target/test-classes/"
            },
            "keyword": "And "
          },
          {
            "result": {
              "duration": 4313000000,
              "status": "passed"
            },
            "line": 7,
            "name": "open url \"https://programesecure.com\"",
            "match": {
              "arguments": [
                {
                  "val": "\"https://programesecure.com\"",
                  "offset": 9
                }
              ],
              "location": "com.tau.steps.GooglePageStep.openUrl(String) in file:/C:/Users/achat/IdeaProjects/tau-cucumber-course/target/test-classes/"
            },
            "keyword": "And "
          }
        ]
      }
    ],
    "name": "This is simple google page search",
    "description": "",
    "id": "this-is-simple-google-page-search",
    "keyword": "Feature",
    "uri": "file:src/test/resources/google2.feature",
    "tags": []
  }
]